{"info":{"amc":"Nippon India Mutual Fund","amfiCode":"102847","schemeName":"Nippon India Balanced Advantage Fund-Growth Plan-Bonus Option","categoryRaw":"Open Ended Schemes ( Hybrid Scheme - Dynamic Asset Allocation or Balanced Advantage )","type":"Open Ended Schemes","categoryFull":"Hybrid Scheme - Dynamic Asset Allocation or Balanced Advantage","scheme":"Hybrid Scheme","category":"Dynamic Asset Allocation or Balanced Advantage","isinGrowth":"INF204K01596","isinDivReinvestment":"","navCount":8,"navStartDate":"2026-05-04","navEndDate":"2026-05-13"},"navs":{"2026-05-13":176.1002,"2026-05-12":175.9059,"2026-05-11":178.0354,"2026-05-08":179.6526,"2026-05-07":180.2041,"2026-05-06":179.9294,"2026-05-05":178.3973,"2026-05-04":178.544}}