{"info":{"amc":"Aditya Birla Sun Life Mutual Fund","amfiCode":"115512","schemeName":"Aditya Birla Sun Life Nifty 50 ETF","categoryRaw":"Open Ended Schemes ( Other Scheme - Other  ETFs )","type":"Open Ended Schemes","categoryFull":"Other Scheme - Other  ETFs","scheme":"Other Scheme","category":"Other  ETFs","isinGrowth":"INF209KB19D1","isinDivReinvestment":"","navCount":8,"navStartDate":"2026-05-04","navEndDate":"2026-05-13"},"navs":{"2026-05-13":27.2638,"2026-05-12":27.2253,"2026-05-11":27.7333,"2026-05-08":28.1529,"2026-05-07":28.3281,"2026-05-06":28.3331,"2026-05-05":27.986,"2026-05-04":28.0868}}