{"info":{"amc":"Canara Robeco Mutual Fund","amfiCode":"118282","schemeName":"CANARA ROBECO INCOME FUND - DIRECT PLAN - GROWTH OPTION","categoryRaw":"Open Ended Schemes ( Debt Scheme - Medium to Long Duration Fund )","type":"Open Ended Schemes","categoryFull":"Debt Scheme - Medium to Long Duration Fund","scheme":"Debt Scheme","category":"Medium to Long Duration Fund","isinGrowth":"INF760K01FI1","isinDivReinvestment":"","navCount":8,"navStartDate":"2026-05-04","navEndDate":"2026-05-13"},"navs":{"2026-05-13":63.3169,"2026-05-12":63.2988,"2026-05-11":63.3529,"2026-05-08":63.4673,"2026-05-07":63.5345,"2026-05-06":63.5268,"2026-05-05":63.335,"2026-05-04":63.3193}}