{"info":{"amc":"Nippon India Mutual Fund","amfiCode":"118585","schemeName":"Nippon India Arbitrage Fund - Direct Plan Growth Plan - Growth Option","categoryRaw":"Open Ended Schemes ( Hybrid Scheme - Arbitrage Fund )","type":"Open Ended Schemes","categoryFull":"Hybrid Scheme - Arbitrage Fund","scheme":"Hybrid Scheme","category":"Arbitrage Fund","isinGrowth":"INF204K01XZ7","isinDivReinvestment":"","navCount":8,"navStartDate":"2026-05-04","navEndDate":"2026-05-13"},"navs":{"2026-05-13":30.2719,"2026-05-12":30.2771,"2026-05-11":30.278,"2026-05-08":30.2695,"2026-05-07":30.2504,"2026-05-06":30.2068,"2026-05-05":30.2391,"2026-05-04":30.2304}}