{"info":{"amc":"ICICI Prudential Mutual Fund","amfiCode":"120251","schemeName":"ICICI Prudential Equity & Debt Fund - Direct Plan - Growth","categoryRaw":"Open Ended Schemes ( Hybrid Scheme - Aggressive Hybrid Fund )","type":"Open Ended Schemes","categoryFull":"Hybrid Scheme - Aggressive Hybrid Fund","scheme":"Hybrid Scheme","category":"Aggressive Hybrid Fund","isinGrowth":"INF109K01Y07","isinDivReinvestment":"","navCount":8,"navStartDate":"2026-05-04","navEndDate":"2026-05-13"},"navs":{"2026-05-13":439.24,"2026-05-12":439.12,"2026-05-11":444.94,"2026-05-08":449.63,"2026-05-07":451.16,"2026-05-06":450.46,"2026-05-05":445.51,"2026-05-04":447.08}}