{"info":{"amc":"JM Financial Mutual Fund","amfiCode":"133395","schemeName":"JM Arbitrage Fund (Direct) - Annual Bonus Option - Principal Units","categoryRaw":"Open Ended Schemes ( Hybrid Scheme - Arbitrage Fund )","type":"Open Ended Schemes","categoryFull":"Hybrid Scheme - Arbitrage Fund","scheme":"Hybrid Scheme","category":"Arbitrage Fund","isinGrowth":"INF192K01GX4","isinDivReinvestment":"","navCount":8,"navStartDate":"2026-05-04","navEndDate":"2026-05-13"},"navs":{"2026-05-13":18.815,"2026-05-12":18.8195,"2026-05-11":18.8148,"2026-05-08":18.8097,"2026-05-07":18.7985,"2026-05-06":18.7684,"2026-05-05":18.7882,"2026-05-04":18.784}}