{"info":{"amc":"Mahindra Manulife Mutual Fund","amfiCode":"140613","schemeName":"Mahindra Manulife Low Duration Fund - Direct Plan -Growth","categoryRaw":"Open Ended Schemes ( Debt Scheme - Low Duration Fund )","type":"Open Ended Schemes","categoryFull":"Debt Scheme - Low Duration Fund","scheme":"Debt Scheme","category":"Low Duration Fund","isinGrowth":"INF174V01267","isinDivReinvestment":"","navCount":8,"navStartDate":"2026-05-04","navEndDate":"2026-05-13"},"navs":{"2026-05-13":1849.602,"2026-05-12":1849.738,"2026-05-11":1849.9606,"2026-05-08":1849.7426,"2026-05-07":1849.4348,"2026-05-06":1848.7945,"2026-05-05":1847.7551,"2026-05-04":1847.9113}}