{"info":{"amc":"Kotak Mahindra Mutual Fund","amfiCode":"144335","schemeName":"Kotak Balanced Advantage Fund  - Direct Plan -Growth Option","categoryRaw":"Open Ended Schemes ( Hybrid Scheme - Dynamic Asset Allocation or Balanced Advantage )","type":"Open Ended Schemes","categoryFull":"Hybrid Scheme - Dynamic Asset Allocation or Balanced Advantage","scheme":"Hybrid Scheme","category":"Dynamic Asset Allocation or Balanced Advantage","isinGrowth":"INF174KA1210","isinDivReinvestment":"","navCount":8,"navStartDate":"2026-05-04","navEndDate":"2026-05-13"},"navs":{"2026-05-13":22.145,"2026-05-12":22.121,"2026-05-11":22.422,"2026-05-08":22.636,"2026-05-07":22.721,"2026-05-06":22.668,"2026-05-05":22.454,"2026-05-04":22.495}}