{"info":{"amc":"Bank of India Mutual Fund","amfiCode":"145678","schemeName":"BANK OF INDIA Small Cap Fund Direct Plan Growth","categoryRaw":"Open Ended Schemes ( Equity Scheme - Small Cap Fund )","type":"Open Ended Schemes","categoryFull":"Equity Scheme - Small Cap Fund","scheme":"Equity Scheme","category":"Small Cap Fund","isinGrowth":"INF761K01EP7","isinDivReinvestment":"","navCount":8,"navStartDate":"2026-05-04","navEndDate":"2026-05-13"},"navs":{"2026-05-13":55.78,"2026-05-12":55.48,"2026-05-11":56.79,"2026-05-08":57.31,"2026-05-07":57.09,"2026-05-06":56.18,"2026-05-05":55.72,"2026-05-04":55.46}}