{"info":{"amc":"Union Mutual Fund","amfiCode":"147003","schemeName":"Union Overnight Fund - Direct Plan - Growth Option","categoryRaw":"Open Ended Schemes ( Debt Scheme - Overnight Fund )","type":"Open Ended Schemes","categoryFull":"Debt Scheme - Overnight Fund","scheme":"Debt Scheme","category":"Overnight Fund","isinGrowth":"INF582M01FA2","isinDivReinvestment":"","navCount":13,"navStartDate":"2026-05-01","navEndDate":"2026-05-13"},"navs":{"2026-05-13":1426.2413,"2026-05-12":1426.0464,"2026-05-11":1425.8483,"2026-05-10":1425.6503,"2026-05-09":1425.4507,"2026-05-08":1425.251,"2026-05-07":1425.057,"2026-05-06":1424.8626,"2026-05-05":1424.6674,"2026-05-04":1424.4715,"2026-05-03":1424.275,"2026-05-02":1424.0691,"2026-05-01":1423.8632}}