{"info":{"amc":"Mirae Asset Mutual Fund","amfiCode":"147445","schemeName":"Mirae Asset Midcap Fund- Direct Growth Option","categoryRaw":"Open Ended Schemes ( Equity Scheme - Mid Cap Fund )","type":"Open Ended Schemes","categoryFull":"Equity Scheme - Mid Cap Fund","scheme":"Equity Scheme","category":"Mid Cap Fund","isinGrowth":"INF769K01FA9","isinDivReinvestment":"","navCount":8,"navStartDate":"2026-05-04","navEndDate":"2026-05-13"},"navs":{"2026-05-13":40.643,"2026-05-12":40.354,"2026-05-11":41.333,"2026-05-08":41.835,"2026-05-07":42.031,"2026-05-06":41.501,"2026-05-05":40.821,"2026-05-04":40.92}}