{"info":{"amc":"Aditya Birla Sun Life Mutual Fund","amfiCode":"147407","schemeName":"Aditya Birla Sun Life Pharma and Healthcare Fund-Regular-Growth","categoryRaw":"Open Ended Schemes ( Equity Scheme - Sectoral/ Thematic )","type":"Open Ended Schemes","categoryFull":"Equity Scheme - Sectoral/ Thematic","scheme":"Equity Scheme","category":"Sectoral/ Thematic","isinGrowth":"INF209KB1N91","isinDivReinvestment":"","navCount":8,"navStartDate":"2026-05-04","navEndDate":"2026-05-13"},"navs":{"2026-05-13":32.79,"2026-05-12":32.73,"2026-05-11":33.34,"2026-05-08":33.08,"2026-05-07":32.89,"2026-05-06":32.78,"2026-05-05":32.12,"2026-05-04":32.06}}