{"info":{"amc":"Axis Mutual Fund","amfiCode":"149049","schemeName":"Axis Floater Fund - Direct Plan - Growth","categoryRaw":"Open Ended Schemes ( Debt Scheme - Floater Fund )","type":"Open Ended Schemes","categoryFull":"Debt Scheme - Floater Fund","scheme":"Debt Scheme","category":"Floater Fund","isinGrowth":"INF846K014A6","isinDivReinvestment":"","navCount":8,"navStartDate":"2026-05-04","navEndDate":"2026-05-13"},"navs":{"2026-05-13":1379.0488,"2026-05-12":1378.5054,"2026-05-11":1380.0868,"2026-05-08":1382.0723,"2026-05-07":1383.0879,"2026-05-06":1382.9862,"2026-05-05":1378.7512,"2026-05-04":1379.345}}