{"info":{"amc":"Mahindra Manulife Mutual Fund","amfiCode":"149104","schemeName":"Mahindra Manulife Flexi Cap Fund - Direct Plan -Growth","categoryRaw":"Open Ended Schemes ( Equity Scheme - Flexi Cap Fund )","type":"Open Ended Schemes","categoryFull":"Equity Scheme - Flexi Cap Fund","scheme":"Equity Scheme","category":"Flexi Cap Fund","isinGrowth":"INF174V01AS2","isinDivReinvestment":"","navCount":8,"navStartDate":"2026-05-04","navEndDate":"2026-05-13"},"navs":{"2026-05-13":16.6115,"2026-05-12":16.5538,"2026-05-11":16.9135,"2026-05-08":17.109,"2026-05-07":17.1713,"2026-05-06":17.1511,"2026-05-05":16.9157,"2026-05-04":17.0122}}