{"info":{"amc":"Sundaram Mutual Fund","amfiCode":"149550","schemeName":"Sundaram Arbitrage Fund (Formerly Known as Prinicpal Arbitrage Fund) - Direct Plan - Growth","categoryRaw":"Open Ended Schemes ( Hybrid Scheme - Arbitrage Fund )","type":"Open Ended Schemes","categoryFull":"Hybrid Scheme - Arbitrage Fund","scheme":"Hybrid Scheme","category":"Arbitrage Fund","isinGrowth":"INF173K01NF7","isinDivReinvestment":"","navCount":8,"navStartDate":"2026-05-04","navEndDate":"2026-05-13"},"navs":{"2026-05-13":16.1031,"2026-05-12":16.1117,"2026-05-11":16.1051,"2026-05-08":16.0962,"2026-05-07":16.0904,"2026-05-06":16.0662,"2026-05-05":16.0849,"2026-05-04":16.0781}}