{"info":{"amc":"Edelweiss Mutual Fund","amfiCode":"150987","schemeName":"BHARAT Bond ETF - April 2033","categoryRaw":"Open Ended Schemes ( Other Scheme - Other  ETFs )","type":"Open Ended Schemes","categoryFull":"Other Scheme - Other  ETFs","scheme":"Other Scheme","category":"Other  ETFs","isinGrowth":"INF754K01QX0","isinDivReinvestment":"","navCount":8,"navStartDate":"2026-05-04","navEndDate":"2026-05-13"},"navs":{"2026-05-13":1274.1226,"2026-05-12":1274.5187,"2026-05-11":1274.9506,"2026-05-08":1275.531,"2026-05-07":1275.8712,"2026-05-06":1274.6871,"2026-05-05":1270.6399,"2026-05-04":1271.1872}}