{"info":{"amc":"Aditya Birla Sun Life Mutual Fund","amfiCode":"152142","schemeName":"Aditya Birla Sun Life US Treasury 1-3 Year Bond ETFs Fund Of Funds-Regular Growth","categoryRaw":"Open Ended Schemes ( Other Scheme - FoF Overseas )","type":"Open Ended Schemes","categoryFull":"Other Scheme - FoF Overseas","scheme":"Other Scheme","category":"FoF Overseas","isinGrowth":"INF209KB13W4","isinDivReinvestment":"","navCount":8,"navStartDate":"2026-05-04","navEndDate":"2026-05-13"},"navs":{"2026-05-13":12.8178,"2026-05-12":12.8081,"2026-05-11":12.7831,"2026-05-08":12.6764,"2026-05-07":12.6499,"2026-05-06":12.696,"2026-05-05":12.7685,"2026-05-04":12.7472}}