{"info":{"amc":"Zerodha Mutual Fund","amfiCode":"152327","schemeName":"Zerodha Nifty 1D Rate Liquid ETF - Growth Option","categoryRaw":"Open Ended Schemes ( Other Scheme - Other  ETFs )","type":"Open Ended Schemes","categoryFull":"Other Scheme - Other  ETFs","scheme":"Other Scheme","category":"Other  ETFs","isinGrowth":"INF0R8F01034","isinDivReinvestment":"","navCount":10,"navStartDate":"2026-05-03","navEndDate":"2026-05-13"},"navs":{"2026-05-13":114.0341,"2026-05-12":114.0191,"2026-05-11":114.004,"2026-05-10":113.9888,"2026-05-08":113.9587,"2026-05-07":113.9437,"2026-05-06":113.9288,"2026-05-05":113.914,"2026-05-04":113.8992,"2026-05-03":113.8844}}