{"info":{"amc":"DSP Mutual Fund","amfiCode":"152653","schemeName":"DSP Nifty Bank Index Fund - Regular - Growth","categoryRaw":"Open Ended Schemes ( Other Scheme - Index Funds )","type":"Open Ended Schemes","categoryFull":"Other Scheme - Index Funds","scheme":"Other Scheme","category":"Index Funds","isinGrowth":"INF740KA1UN8","isinDivReinvestment":"","navCount":8,"navStartDate":"2026-05-04","navEndDate":"2026-05-13"},"navs":{"2026-05-13":10.8281,"2026-05-12":10.8484,"2026-05-11":11.0275,"2026-05-08":11.2039,"2026-05-07":11.3534,"2026-05-06":11.3403,"2026-05-05":11.0502,"2026-05-04":11.1175}}