{"info":{"amc":"Bajaj Finserv Mutual Fund","amfiCode":"152642","schemeName":"Bajaj Finserv Multi Asset Allocation Fund - Regular Growth","categoryRaw":"Open Ended Schemes ( Hybrid Scheme - Multi Asset Allocation )","type":"Open Ended Schemes","categoryFull":"Hybrid Scheme - Multi Asset Allocation","scheme":"Hybrid Scheme","category":"Multi Asset Allocation","isinGrowth":"INF0QA701797","isinDivReinvestment":"","navCount":8,"navStartDate":"2026-05-04","navEndDate":"2026-05-13"},"navs":{"2026-05-13":12.0593,"2026-05-12":11.9153,"2026-05-11":12.0016,"2026-05-08":12.1412,"2026-05-07":12.1728,"2026-05-06":12.1502,"2026-05-05":12.0297,"2026-05-04":12.047}}