{"info":{"amc":"Groww Mutual Fund","amfiCode":"154057","schemeName":"Groww Multi Asset Omni FOF Regular Growth","categoryRaw":"Open Ended Schemes ( Other Scheme - FoF Domestic )","type":"Open Ended Schemes","categoryFull":"Other Scheme - FoF Domestic","scheme":"Other Scheme","category":"FoF Domestic","isinGrowth":"INF666M01NF6","isinDivReinvestment":"","navCount":8,"navStartDate":"2026-05-04","navEndDate":"2026-05-13"},"navs":{"2026-05-13":10.0084,"2026-05-12":9.9197,"2026-05-11":10.0731,"2026-05-08":10.185,"2026-05-07":10.1885,"2026-05-06":10.1149,"2026-05-05":9.975,"2026-05-04":9.9828}}