{"info":{"amc":"Jio BlackRock Mutual Fund","amfiCode":"154079","schemeName":"JioBlackRock Short Duration Fund - Direct Plan - Growth Option","categoryRaw":"Open Ended Schemes ( Debt Scheme - Short Duration Fund )","type":"Open Ended Schemes","categoryFull":"Debt Scheme - Short Duration Fund","scheme":"Debt Scheme","category":"Short Duration Fund","isinGrowth":"INF22M001143","isinDivReinvestment":"","navCount":8,"navStartDate":"2026-05-04","navEndDate":"2026-05-13"},"navs":{"2026-05-13":1015.2518,"2026-05-12":1015.3557,"2026-05-11":1015.4186,"2026-05-08":1015.3927,"2026-05-07":1015.2163,"2026-05-06":1014.985,"2026-05-05":1014.35,"2026-05-04":1014.4203}}