{"info":{"amc":"Abakkus Mutual Fund","amfiCode":"154043","schemeName":"Abakkus Flexi Cap Fund - Direct - Growth","categoryRaw":"Open Ended Schemes ( Equity Scheme - Flexi Cap Fund )","type":"Open Ended Schemes","categoryFull":"Equity Scheme - Flexi Cap Fund","scheme":"Equity Scheme","category":"Flexi Cap Fund","isinGrowth":"INF2JJD01136","isinDivReinvestment":"","navCount":8,"navStartDate":"2026-05-04","navEndDate":"2026-05-13"},"navs":{"2026-05-13":10.164,"2026-05-12":10.124,"2026-05-11":10.337,"2026-05-08":10.478,"2026-05-07":10.543,"2026-05-06":10.471,"2026-05-05":10.316,"2026-05-04":10.352}}